simple_zmq/__init__.py
simple_zmq/pub_sub.py
simple_zmq/push_pull.py
simple_zmq/req_rep.py
simple_zmq/utils.py
simple_zmq-0.1.4.dist-info/DESCRIPTION.rst
simple_zmq-0.1.4.dist-info/METADATA
simple_zmq-0.1.4.dist-info/RECORD
simple_zmq-0.1.4.dist-info/WHEEL
simple_zmq-0.1.4.dist-info/metadata.json
simple_zmq-0.1.4.dist-info/top_level.txt
